MANIFEST.in
README.rst
setup.py
django_urlmapper.egg-info/PKG-INFO
django_urlmapper.egg-info/SOURCES.txt
django_urlmapper.egg-info/dependency_links.txt
django_urlmapper.egg-info/not-zip-safe
django_urlmapper.egg-info/top_level.txt
urlmapper/__init__.py
urlmapper/tests.py
urlmapper/utils.py