Metadata-Version: 1.1
Name: django-urlmapper
Version: 1.1.0
Summary: Print registered urls in a readable format.
Home-page: https://github.com/prestontimmons/django-urlmapper
Author: Preston Timmons
Author-email: prestontimmons@gmail.com
License: UNKNOWN
Platform: UNKNOWN
Classifier: Framework :: Django
Classifier: License :: OSI Approved :: MIT License
Classifier: Programming Language :: Python
Classifier: Programming Language :: Python :: 2.7
Classifier: Programming Language :: Python :: 3.3
Classifier: Programming Language :: Python :: 3.4
